mesomath/__about__.py
mesomath/__init__.py
mesomath/babcalc.py
mesomath/babn.py
mesomath/hamming.py
mesomath/metrotable.py
mesomath/mtlookup.py
mesomath/multable.py
mesomath/npvs.py
mesomath-1.2.2.dist-info/METADATA
mesomath-1.2.2.dist-info/WHEEL
mesomath-1.2.2.dist-info/entry_points.txt
mesomath-1.2.2.dist-info/licenses/LICENSE
mesomath-1.2.2.dist-info/RECORD
