Metadata-Version: 2.4
Name: mesomath
Version: 1.2.2
Summary: Mesopotamian Calculator
Project-URL: Homepage, https:mesomath.readthedocs.io
Project-URL: Issues, https://github.com/jccsvq/mesomath/issues
Project-URL: Source, https://github.com/jccsvq/mesomath
Author-email: Jesús Cabrera <jccsvq@gmail.com>
License-Expression: CC0-1.0
License-File: LICENSE
Keywords: arithmetic,calculator,command-line,mesopotamia,metrology,sexagesimal
Classifier: Development Status :: 5 - Production/Stable
Classifier: Environment :: Console
Classifier: Intended Audience :: Education
Classifier: Intended Audience :: Science/Research
Classifier: Operating System :: OS Independent
Classifier: Programming Language :: Python
Classifier: Programming Language :: Python :: 3.10
Classifier: Programming Language :: Python :: 3.11
Classifier: Programming Language :: Python :: 3.12
Classifier: Programming Language :: Python :: Implementation :: CPython
Classifier: Programming Language :: Python :: Implementation :: PyPy
Classifier: Topic :: Scientific/Engineering :: Mathematics
Requires-Python: >=3.10
